terra_sdk/__init__.py
terra_sdk/client/__init__.py
terra_sdk/client/lcd/__init__.py
terra_sdk/client/lcd/api/__init__.py
terra_sdk/client/lcd/api/_base.py
terra_sdk/client/lcd/api/auth.py
terra_sdk/client/lcd/api/authz.py
terra_sdk/client/lcd/api/bank.py
terra_sdk/client/lcd/api/distribution.py
terra_sdk/client/lcd/api/feegrant.py
terra_sdk/client/lcd/api/gov.py
terra_sdk/client/lcd/api/ibc.py
terra_sdk/client/lcd/api/ibc_transfer.py
terra_sdk/client/lcd/api/mint.py
terra_sdk/client/lcd/api/slashing.py
terra_sdk/client/lcd/api/staking.py
terra_sdk/client/lcd/api/tendermint.py
terra_sdk/client/lcd/api/tx.py
terra_sdk/client/lcd/api/wasm.py
terra_sdk/client/lcd/lcdclient.py
terra_sdk/client/lcd/lcdutils.py
terra_sdk/client/lcd/params.py
terra_sdk/client/lcd/wallet.py
terra_sdk/client/localterra.py
terra_sdk/core/__init__.py
terra_sdk/core/auth/__init__.py
terra_sdk/core/auth/data/__init__.py
terra_sdk/core/auth/data/account.py
terra_sdk/core/auth/data/base_account.py
terra_sdk/core/auth/data/base_vesting_account.py
terra_sdk/core/auth/data/continuous_vesting_account.py
terra_sdk/core/auth/data/delayed_vesting_account.py
terra_sdk/core/auth/data/periodic_vesting_account.py
terra_sdk/core/auth/msgs/__init__.py
terra_sdk/core/auth/msgs/msg_create_periodic_vesting_account.py
terra_sdk/core/auth/msgs/msg_create_vesting_account.py
terra_sdk/core/auth/msgs/msg_donate_all_vesting_tokens.py
terra_sdk/core/authz/__init__.py
terra_sdk/core/authz/data.py
terra_sdk/core/authz/msgs.py
terra_sdk/core/bank/__init__.py
terra_sdk/core/bank/msgs.py
terra_sdk/core/bech32.py
terra_sdk/core/block.py
terra_sdk/core/broadcast.py
terra_sdk/core/coin.py
terra_sdk/core/coins.py
terra_sdk/core/compact_bit_array.py
terra_sdk/core/crisis/__init__.py
terra_sdk/core/crisis/msgs.py
terra_sdk/core/deposit.py
terra_sdk/core/distribution/__init__.py
terra_sdk/core/distribution/msgs.py
terra_sdk/core/distribution/proposals.py
terra_sdk/core/fee.py
terra_sdk/core/feegrant/__init__.py
terra_sdk-3.0.1.dist-info/LICENSE
terra_sdk-3.0.1.dist-info/WHEEL
terra_sdk-3.0.1.dist-info/METADATA
terra_sdk-3.0.1.dist-info/RECORD
